LICENSE
MANIFEST.in
README.md
setup.cfg
setup.py
broccoli_server/__init__.py
broccoli_server/application.py
broccoli_server.egg-info/PKG-INFO
broccoli_server.egg-info/SOURCES.txt
broccoli_server.egg-info/dependency_links.txt
broccoli_server.egg-info/not-zip-safe
broccoli_server.egg-info/requires.txt
broccoli_server.egg-info/top_level.txt
broccoli_server/content/__init__.py
broccoli_server/content/content_store.py
broccoli_server/contrib/__init__.py
broccoli_server/contrib/api/__init__.py
broccoli_server/contrib/api/timeline.py
broccoli_server/contrib/job/__init__.py
broccoli_server/contrib/job/example.py
broccoli_server/contrib/mod_view/__init__.py
broccoli_server/contrib/mod_view/echo.py
broccoli_server/contrib/mod_view/update_one_button.py
broccoli_server/contrib/worker/__init__.py
broccoli_server/contrib/worker/example.py
broccoli_server/contrib/worker/twitter_media.py
broccoli_server/contrib/worker/twitter_media_scraper.py
broccoli_server/contrib/worker/utils.py
broccoli_server/interface/__init__.py
broccoli_server/interface/api/__init__.py
broccoli_server/interface/api/api_handler.py
broccoli_server/interface/job/__init__.py
broccoli_server/interface/job/job.py
broccoli_server/interface/job/job_context.py
broccoli_server/interface/mod_view/__init__.py
broccoli_server/interface/mod_view/column.py
broccoli_server/interface/mod_view/column_render.py
broccoli_server/interface/worker/__init__.py
broccoli_server/interface/worker/metadata_store.py
broccoli_server/interface/worker/work_context.py
broccoli_server/interface/worker/worker.py
broccoli_server/job/__init__.py
broccoli_server/job/job_context.py
broccoli_server/job/job_factory.py
broccoli_server/job/job_run.py
broccoli_server/job/job_runs_store.py
broccoli_server/job/job_scheduler.py
broccoli_server/mod_view/__init__.py
broccoli_server/mod_view/mod_view_query.py
broccoli_server/mod_view/mod_view_renderer.py
broccoli_server/mod_view/mod_view_store.py
broccoli_server/pipeline/__init__.py
broccoli_server/pipeline/pipeline.py
broccoli_server/pipeline/pipeline_mod_view.py
broccoli_server/pipeline/pipeline_source.py
broccoli_server/pipeline/pipeline_state.py
broccoli_server/pipeline/pipeline_worker.py
