Metadata-Version: 2.1
Name: broccoli-server
Version: 7.2.8
Summary: A Python framework to build web scraping applications.
Home-page: https://github.com/k-t-corp/broccoli-server
Author: KTachibanaM
Author-email: whj19931115@gmail.com
License-File: LICENSE
